traffic_guardian/__init__.py
traffic_guardian/traffic_guardian_client.py
traffic_guardian_core/__init__.py
traffic_guardian_core/persistency.py
traffic_guardian_core/proxy_rules_govenor.py
traffic_guardian_core/proxy_server.py
traffic_guardian-1.0.3.dist-info/LICENSE.txt
traffic_guardian-1.0.3.dist-info/METADATA
traffic_guardian-1.0.3.dist-info/WHEEL
traffic_guardian-1.0.3.dist-info/entry_points.txt
traffic_guardian-1.0.3.dist-info/top_level.txt
traffic_guardian-1.0.3.dist-info/RECORD
